LICENSE.txt
MANIFEST.in
README.rst
setup.py
docs/Makefile
docs/conf.py
docs/index.rst
tests/.coverage
tests/.coveragerc
tests/test_analysis.py
tests/test_model.py
tests/test_parsing.py
tests/test_recording.py
tests/.pytest_cache/.gitignore
tests/.pytest_cache/CACHEDIR.TAG
tests/.pytest_cache/README.md
tests/.pytest_cache/v/cache/nodeids
tests/.pytest_cache/v/cache/stepwise
tests/demo_games/.coverage
tests/demo_games/2241381.tch
tests/demo_games/2241402.tch
tests/demo_games/300357.tch
tests/demo_games/demo_game.tch
tests/demo_games/incomplete.tch
tests/demo_games/normal_game.tch
tests/demo_games/one_round_grand_tichu.tch
tests/demo_games/one_round_no_tichu.tch
tests/demo_games/one_round_tichu_after.tch
tests/demo_games/one_round_tichu_before.tch
tests/demo_games/player_swap.tch
tests/demo_games/two_rounds_grand_tichus_diff_seats.tch
tests/htmlcov/_home_kale_hacking_projects_tich_me_tich_me___init___py.html
tests/htmlcov/_home_kale_hacking_projects_tich_me_tich_me_analysis_py.html
tests/htmlcov/_home_kale_hacking_projects_tich_me_tich_me_app_py.html
tests/htmlcov/_home_kale_hacking_projects_tich_me_tich_me_main_py.html
tests/htmlcov/_home_kale_hacking_projects_tich_me_tich_me_model_py.html
tests/htmlcov/_home_kale_hacking_projects_tich_me_tich_me_scrape_py.html
tests/htmlcov/coverage_html.js
tests/htmlcov/index.html
tests/htmlcov/jquery.ba-throttle-debounce.min.js
tests/htmlcov/jquery.hotkeys.js
tests/htmlcov/jquery.isonscreen.js
tests/htmlcov/jquery.min.js
tests/htmlcov/jquery.tablesorter.min.js
tests/htmlcov/keybd_closed.png
tests/htmlcov/keybd_open.png
tests/htmlcov/status.json
tests/htmlcov/style.css
tich_me/__init__.py
tich_me/analysis.py
tich_me/app.py
tich_me/main.py
tich_me/model.py
tich_me/scrape.py
tich_me.egg-info/PKG-INFO
tich_me.egg-info/SOURCES.txt
tich_me.egg-info/dependency_links.txt
tich_me.egg-info/entry_points.txt
tich_me.egg-info/requires.txt
tich_me.egg-info/top_level.txt