Metadata-Version: 1.1
Name: tich-me
Version: 0.1.3
Summary: UNKNOWN
Home-page: UNKNOWN
Author: Kale Kundert
Author-email: kale@thekunderts.net
License: UNKNOWN
Platform: UNKNOWN
Classifier: Programming Language :: Python :: 3.6
Classifier: Topic :: Games/Entertainment :: Board Games
Classifier: License :: OSI Approved :: GNU General Public License v3 or later (GPLv3+)
Classifier: Natural Language :: English
